{
  "$schema": "https://json-structure.org/meta/core/v0/#",
  "$id": "https://raw.githubusercontent.com/api-evangelist/otter/refs/heads/main/json-structure/public-api-order-identifier-structure.json",
  "name": "OrderIdentifier",
  "description": "The external identifiers of the order.",
  "type": "object",
  "properties": {
    "id": {
      "type": "string",
      "description": "Unique ID for the order that was placed.",
      "example": "69f60a06-c335-46d9-b5a1-97f1a211c514"
    },
    "source": {
      "type": "string",
      "description": "Describes the source of the order, typically from a food ordering marketplace.",
      "example": "ubereats"
    }
  },
  "required": [
    "id",
    "source"
  ]
}